[ {
  "zip" : "gfgf",
  "firstName" : "visjhall",
  "lastName" : "oirt",
  "address" : "yujyv",
  "phoneNumber" : "dg",
  "city" : "frt",
  "state" : "uikybh"
}, {
  "zip" : "ldf",
  "firstName" : "ijdfld",
  "lastName" : "dkljfl",
  "address" : "dljfx",
  "phoneNumber" : ";fdk;l",
  "city" : "dfjl",
  "state" : "kdf"
}, {
  "zip" : "4653",
  "firstName" : "dfkj",
  "lastName" : "ldfsjk",
  "address" : "ljdk",
  "phoneNumber" : "786532",
  "city" : "fl",
  "state" : "ldjk"
}, {
  "zip" : "kldfj",
  "firstName" : "ddkfdkj",
  "lastName" : "ljkgf",
  "address" : "jkdfhdl",
  "phoneNumber" : "jkdf",
  "city" : "ld;fk",
  "state" : "d;fkl"
} ]